pymupdf_img/__init__.py
pymupdf_img/cli.py
pymupdf_img/const.py
pymupdf_img/core.py
pymupdf_img-0.1.1.dist-info/METADATA
pymupdf_img-0.1.1.dist-info/WHEEL
pymupdf_img-0.1.1.dist-info/entry_points.txt
pymupdf_img-0.1.1.dist-info/licenses/LICENSE
pymupdf_img-0.1.1.dist-info/RECORD
