Metadata-Version: 2.4
Name: pymupdf-img
Version: 0.1.1
Summary: Fast PDF to image converter with batch processing and multi-threading
Project-URL: Homepage, https://github.com/Segolene-Albouy/pdf-to-img
Project-URL: Repository, https://github.com/Segolene-Albouy/pdf-to-img
Project-URL: Issues, https://github.com/Segolene-Albouy/pdf-to-img/issues
Author-email: SÃ©golÃ¨ne Albouy <segolene.albouy@gmail.com>
License: GPL-3.0-or-later
License-File: LICENSE
Keywords: batch,converter,image,pdf,pymupdf
Classifier: Development Status :: 4 - Beta
Classifier: Intended Audience :: Developers
Classifier: License :: OSI Approved :: GNU General Public License v3 or later (GPLv3+)
Classifier: Programming Language :: Python :: 3
Classifier: Programming Language :: Python :: 3.8
Classifier: Programming Language :: Python :: 3.9
Classifier: Programming Language :: Python :: 3.10
Classifier: Programming Language :: Python :: 3.11
Classifier: Programming Language :: Python :: 3.12
Classifier: Topic :: Multimedia :: Graphics :: Graphics Conversion
Requires-Python: >=3.8
Requires-Dist: pymupdf>=1.23.0
